{
"type": "FeatureCollection",
"name": "food_make_cents",
"crs": { "type": "name", "properties": { "name": "urn:ogc:def:crs:OGC:1.3:CRS84" } },
"features": [
{ "type": "Feature", "properties": { "Name": "Make Cents", "description": "Clubhouse Deli<br>Mini salad: 1.75<br>- Add deli meat: 1.95<br>½ sandwich: 3.10<br>Grilled cheese: 2.75<br>Small soup: 2.15<br>Whole fruit: .75" }, "geometry": { "type": "Point", "coordinates": [ -123.283505, 44.563967, 0.0 ] } },
{ "type": "Feature", "properties": { "Name": "Make Cents", "description": "Calabaloo’s<br>Side grilled chicken breast: 2.65<br>Grilled pineapple:1.25" }, "geometry": { "type": "Point", "coordinates": [ -123.2836, 44.564039, 0.0 ] } },
{ "type": "Feature", "properties": { "Name": "Make Cents", "description": "Ring of Fire<br>Brown rice or white: 1.00<br>Stir fry vegetables: 1.55" }, "geometry": { "type": "Point", "coordinates": [ -123.283363, 44.564036, 0.0 ] } },
{ "type": "Feature", "properties": { "Name": "Make Cents", "description": "Tomasitto’s<br>Seasonal vegetable: 1.00<br>Small pasta w\/ sauce: 2.50<br>Vegetarian or meat pizza slice: 3.00<br>Whole fruit: .75" }, "geometry": { "type": "Point", "coordinates": [ -123.28333, 44.563965, 0.0 ] } },
{ "type": "Feature", "properties": { "Name": "Make Cents", "description": "Seasonal vegetable: 1.00<br>Grain\/starch side (potatoes, rice, corn): 1.00" }, "geometry": { "type": "Point", "coordinates": [ -123.283225, 44.564027, 0.0 ] } },
{ "type": "Feature", "properties": { "Name": "Make Cents", "description": "Serrano’s<br>Single taco: 2.00<br>Side quinoa, brown rice or cilantro rice: 1.00<br>Side pinto or black beans: 1.00" }, "geometry": { "type": "Point", "coordinates": [ -123.283253, 44.563954, 0.0 ] } },
{ "type": "Feature", "properties": { "Name": "Make Cents", "description": "Boardwalk<br>Mini salad: 1.75<br>Small vegetarian chili: 2.15<br>Small soup of the day: 2.15<br>Whole fruit: .75<br>Seasonal vegetable: 1.00<br>Grain\/starch side (potatoes, rice, corn): 1.00<br>Baked potato w\/ toppings: $2.00" }, "geometry": { "type": "Point", "coordinates": [ -123.272014, 44.563983, 0.0 ] } },
{ "type": "Feature", "properties": { "Name": "Make Cents", "description": "Calabaloo’s<br>Side grilled chicken breast: 2.65<br>Grilled pineapple: 1.25" }, "geometry": { "type": "Point", "coordinates": [ -123.271965, 44.564058, 0.0 ] } },
{ "type": "Feature", "properties": { "Name": "Make Cents", "description": "Salad Bar\/Soup Station<br>Mini salad: 1.75<br>Small vegetarian chili: 2.15<br>Small soup of the day: 2.15<br>Whole fruit: .75" }, "geometry": { "type": "Point", "coordinates": [ -123.277674, 44.560808, 0.0 ] } },
{ "type": "Feature", "properties": { "Name": "Make Cents", "description": "Deli<br>½ sandwich: 3.10<br>Grilled cheese: 2.75" }, "geometry": { "type": "Point", "coordinates": [ -123.277674, 44.560775, 0.0 ] } },
{ "type": "Feature", "properties": { "Name": "Make Cents", "description": "Grill<br>Side grilled chicken breast: 2.65" }, "geometry": { "type": "Point", "coordinates": [ -123.27769, 44.560695, 0.0 ] } },
{ "type": "Feature", "properties": { "Name": "Make Cents", "description": "Pizza<br>Vegetarian or meat pizza slice: 3.00" }, "geometry": { "type": "Point", "coordinates": [ -123.2776, 44.560832, 0.0 ] } },
{ "type": "Feature", "properties": { "Name": "Make Cents", "description": "Global Fare<br>Seasonal vegetable: 1.00<br>Grain\/starch side (potatoes, rice, corn, beans): 1.00" }, "geometry": { "type": "Point", "coordinates": [ -123.277691, 44.560624, 0.0 ] } }
]
}
